mistralai_workflows/plugins/mistralai/__init__.py
mistralai_workflows/plugins/mistralai/activities.py
mistralai_workflows/plugins/mistralai/lechat.py
mistralai_workflows/plugins/mistralai/models.py
mistralai_workflows/plugins/mistralai/py.typed
mistralai_workflows/plugins/mistralai/utils.py
mistralai_workflows_plugins_mistralai-2.0.0rc12.dist-info/METADATA
mistralai_workflows_plugins_mistralai-2.0.0rc12.dist-info/WHEEL
mistralai_workflows_plugins_mistralai-2.0.0rc12.dist-info/licenses/LICENSE
mistralai_workflows_plugins_mistralai-2.0.0rc12.dist-info/RECORD
