Metadata-Version: 2.4
Name: mistralai-workflows-plugins-mistralai
Version: 2.0.0rc12
Summary: Mistral AI plugin for Mistral Workflows - Provides native Mistral AI integration
Project-URL: Homepage, https://mistral.ai
Project-URL: Documentation, https://docs-internal-frameworks.mistral.ai/workflows
Author-email: Mistral AI <support@mistral.ai>
License: Apache-2.0
License-File: LICENSE
Keywords: ai,llm,mistral,plugin,workflows
Classifier: Development Status :: 4 - Beta
Classifier: Intended Audience :: Developers
Classifier: License :: OSI Approved :: Apache Software License
Classifier: Programming Language :: Python :: 3
Classifier: Programming Language :: Python :: 3.12
Classifier: Topic :: Scientific/Engineering :: Artificial Intelligence
Classifier: Topic :: Software Development :: Libraries :: Python Modules
Requires-Python: <3.13,>=3.12
Requires-Dist: mistralai-workflows<2.1.0,>=2.0.0rc1
Requires-Dist: mistralai>=1.8.1
Requires-Dist: structlog<26,>=24
